precommit_changeid/__init__.py
precommit_changeid-1.0.dist-info/METADATA
precommit_changeid-1.0.dist-info/WHEEL
precommit_changeid-1.0.dist-info/entry_points.txt
precommit_changeid-1.0.dist-info/top_level.txt
precommit_changeid-1.0.dist-info/RECORD
